distributionsCB39449
