Metadata-Version: 1.0
Name: distributionsCB39449
Version: 0.2
Summary: Gaussian and Binomial distributions
Home-page: UNKNOWN
Author: Michael J Swickrath
Author-email: michael.swickrath@gmail.com
License: UNKNOWN
Platform: UNKNOWN
